[
 {
  "keywords": [
   [
    "car", 
    3, 
    0.2631578947368421
   ], 
   [
    "minsky", 
    3, 
    0.21052631578947367
   ], 
   [
    "kenya", 
    1, 
    0.10526315789473684
   ], 
   [
    "kasem", 
    3, 
    0.1
   ], 
   [
    "plane", 
    3, 
    0.1
   ], 
   [
    "operation", 
    3, 
    0.1
   ], 
   [
    "khouri", 
    3, 
    0.1
   ], 
   [
    "tit", 
    3, 
    0.1
   ], 
   [
    "tanya", 
    3, 
    0.1
   ], 
   [
    "bangkok", 
    3, 
    0.1
   ], 
   [
    "parts", 
    3, 
    0.05263157894736842
   ], 
   [
    "yemen", 
    1, 
    0.05263157894736842
   ], 
   [
    "lebanon", 
    1, 
    0.05263157894736842
   ], 
   [
    "munitions", 
    3, 
    0.05263157894736842
   ], 
   [
    "boonmee", 
    2, 
    0.03508771929824561
   ], 
   [
    "nicolai", 
    2, 
    0.03508771929824561
   ], 
   [
    "arms", 
    3, 
    0.03508771929824561
   ], 
   [
    "kuryakin", 
    3, 
    0.03508771929824561
   ], 
   [
    "khemkhaengare", 
    3, 
    0.03508771929824561
   ], 
   [
    "dealers", 
    3, 
    0.03508771929824561
   ]
  ], 
  "TopicNum: ": 0
 }, 
 {
  "keywords": [
   [
    "sickness", 
    3, 
    0.125
   ], 
   [
    "jhon", 
    3, 
    0.1
   ], 
   [
    "kiev", 
    3, 
    0.1
   ], 
   [
    "turkey", 
    3, 
    0.1
   ], 
   [
    "borodinski", 
    2, 
    0.08333333333333333
   ], 
   [
    "green", 
    2, 
    0.08333333333333333
   ], 
   [
    "celik", 
    3, 
    0.08333333333333333
   ], 
   [
    "nigeria", 
    1, 
    0.08333333333333333
   ], 
   [
    "george", 
    2, 
    0.08333333333333333
   ], 
   [
    "iran", 
    1, 
    0.041666666666666664
   ], 
   [
    "money", 
    3, 
    0.041666666666666664
   ], 
   [
    "dubai", 
    1, 
    0.041666666666666664
   ], 
   [
    "venezuela", 
    1, 
    0.041666666666666664
   ], 
   [
    "syria", 
    1, 
    0.041666666666666664
   ], 
   [
    "farming", 
    3, 
    0.041666666666666664
   ], 
   [
    "hakan", 
    2, 
    0.041666666666666664
   ], 
   [
    "dombrovski", 
    2, 
    0.041666666666666664
   ], 
   [
    "health", 
    3, 
    0.041666666666666664
   ], 
   [
    "sails", 
    3, 
    0.041666666666666664
   ], 
   [
    "columbia", 
    2, 
    0.041666666666666664
   ]
  ], 
  "TopicNum: ": 1
 }, 
 {
  "keywords": [
   [
    "may", 
    0, 
    0.12
   ], 
   [
    "bukhari", 
    3, 
    0.1
   ], 
   [
    "basra", 
    3, 
    0.1
   ], 
   [
    "belong", 
    3, 
    0.1
   ], 
   [
    "guns", 
    3, 
    0.08
   ], 
   [
    "arms", 
    3, 
    0.08
   ], 
   [
    "ahmed", 
    2, 
    0.08
   ], 
   [
    "otieno", 
    2, 
    0.08
   ], 
   [
    "sudan", 
    1, 
    0.08
   ], 
   [
    "jtomski", 
    2, 
    0.08
   ], 
   [
    "saudi", 
    1, 
    0.04
   ], 
   [
    "parts", 
    3, 
    0.04
   ], 
   [
    "deal", 
    3, 
    0.04
   ], 
   [
    "illegal", 
    3, 
    0.04
   ], 
   [
    "pakistan", 
    1, 
    0.04
   ], 
   [
    "death", 
    3, 
    0.04
   ], 
   [
    "arabia", 
    1, 
    0.04
   ], 
   [
    "onyango", 
    2, 
    0.04
   ], 
   [
    "owiti", 
    2, 
    0.04
   ], 
   [
    "volkswagons", 
    3, 
    0.04
   ]
  ], 
  "TopicNum: ": 2
 }
]