[
 {
  "keywords": [
   [
    "parts", 
    3, 
    0.060453400503778336
   ], 
   [
    "antalya", 
    1, 
    0.060453400503778336
   ], 
   [
    "waterways", 
    3, 
    0.055415617128463476
   ], 
   [
    "contract", 
    3, 
    0.05037783375314862
   ], 
   [
    "stand", 
    3, 
    0.04030226700251889
   ], 
   [
    "nigeria", 
    1, 
    0.037783375314861464
   ], 
   [
    "jhon", 
    2, 
    0.030226700251889168
   ], 
   [
    "textbooks", 
    3, 
    0.030226700251889168
   ], 
   [
    "baltasar", 
    2, 
    0.030226700251889168
   ], 
   [
    "professor", 
    2, 
    0.030226700251889168
   ], 
   [
    "payment", 
    3, 
    0.030226700251889168
   ], 
   [
    "celik", 
    3, 
    0.030226700251889168
   ], 
   [
    "hakan", 
    2, 
    0.030226700251889168
   ], 
   [
    "emerites", 
    3, 
    0.030226700251889168
   ], 
   [
    "george", 
    2, 
    0.030226700251889168
   ], 
   [
    "company", 
    3, 
    0.030226700251889168
   ], 
   [
    "jtomski", 
    2, 
    0.030226700251889168
   ], 
   [
    "vwhombre", 
    2, 
    0.030226700251889168
   ], 
   [
    "pontiac", 
    3, 
    0.030226700251889168
   ], 
   [
    "savvytraveladvice", 
    3, 
    0.030226700251889168
   ]
  ], 
  "TopicNum: ": 0
 }, 
 {
  "keywords": [
   [
    "nairobi", 
    2, 
    0.12244897959183673
   ], 
   [
    "tanya", 
    2, 
    0.08163265306122448
   ], 
   [
    "waterways", 
    3, 
    0.061224489795918366
   ], 
   [
    "protection", 
    3, 
    0.061224489795918366
   ], 
   [
    "regional", 
    3, 
    0.061224489795918366
   ], 
   [
    "guard", 
    3, 
    0.061224489795918366
   ], 
   [
    "kasem", 
    2, 
    0.04081632653061224
   ], 
   [
    "aden", 
    2, 
    0.04081632653061224
   ], 
   [
    "malaysia", 
    1, 
    0.04081632653061224
   ], 
   [
    "lima", 
    3, 
    0.04081632653061224
   ], 
   [
    "shulaf", 
    3, 
    0.04081632653061224
   ], 
   [
    "somalia", 
    1, 
    0.04081632653061224
   ], 
   [
    "general", 
    3, 
    0.04081632653061224
   ], 
   [
    "raleigh", 
    3, 
    0.04081632653061224
   ], 
   [
    "muminin", 
    3, 
    0.04081632653061224
   ], 
   [
    "iran", 
    1, 
    0.02040816326530612
   ], 
   [
    "believed", 
    3, 
    0.02040816326530612
   ], 
   [
    "shipped", 
    3, 
    0.02040816326530612
   ], 
   [
    "chanarong", 
    3, 
    0.02040816326530612
   ], 
   [
    "lebanon", 
    1, 
    0.02040816326530612
   ]
  ], 
  "TopicNum: ": 1
 }, 
 {
  "keywords": [
   [
    "hospital", 
    1, 
    0.34285714285714286
   ], 
   [
    "may", 
    0, 
    0.14285714285714285
   ], 
   [
    "bukhari", 
    2, 
    0.11428571428571428
   ], 
   [
    "khouri", 
    2, 
    0.11428571428571428
   ], 
   [
    "gaza", 
    1, 
    0.11428571428571428
   ], 
   [
    "nairobi", 
    2, 
    0.11428571428571428
   ], 
   [
    "basra", 
    3, 
    0.1
   ], 
   [
    "bukhari", 
    3, 
    0.1
   ], 
   [
    "kiev", 
    3, 
    0.1
   ], 
   [
    "per", 
    3, 
    0.1
   ], 
   [
    "tebilaead", 
    3, 
    0.1
   ], 
   [
    "bank", 
    3, 
    0.1
   ], 
   [
    "ali", 
    3, 
    0.1
   ], 
   [
    "blanks", 
    3, 
    0.1
   ], 
   [
    "lahore", 
    3, 
    0.1
   ], 
   [
    "jhangvi", 
    3, 
    0.1
   ], 
   [
    "left", 
    3, 
    0.1
   ], 
   [
    "residence", 
    3, 
    0.1
   ], 
   [
    "minsky", 
    3, 
    0.1
   ], 
   [
    "pakistan", 
    1, 
    0.05714285714285714
   ]
  ], 
  "TopicNum: ": 2
 }, 
 {
  "keywords": [
   [
    "april", 
    0, 
    0.14634146341463414
   ], 
   [
    "russian", 
    3, 
    0.10975609756097561
   ], 
   [
    "scheduled", 
    3, 
    0.1
   ], 
   [
    "funds", 
    3, 
    0.1
   ], 
   [
    "borodinski", 
    3, 
    0.1
   ], 
   [
    "health", 
    3, 
    0.0975609756097561
   ], 
   [
    "equipment", 
    3, 
    0.07317073170731707
   ], 
   [
    "operation", 
    3, 
    0.07317073170731707
   ], 
   [
    "farming", 
    3, 
    0.07317073170731707
   ], 
   [
    "khemkhaengon", 
    3, 
    0.07317073170731707
   ], 
   [
    "nicolai", 
    2, 
    0.07317073170731707
   ], 
   [
    "dubai", 
    1, 
    0.036585365853658534
   ], 
   [
    "dombrovski", 
    2, 
    0.036585365853658534
   ], 
   [
    "ahmed", 
    2, 
    0.036585365853658534
   ], 
   [
    "saleh", 
    2, 
    0.036585365853658534
   ], 
   [
    "aden", 
    2, 
    0.036585365853658534
   ], 
   [
    "kenya", 
    1, 
    0.036585365853658534
   ], 
   [
    "ministry", 
    3, 
    0.024390243902439025
   ], 
   [
    "may", 
    0, 
    0.018292682926829267
   ], 
   [
    "nigeria", 
    1, 
    0.018292682926829267
   ]
  ], 
  "TopicNum: ": 3
 }, 
 {
  "keywords": [
   [
    "ukrainian", 
    2, 
    0.07228915662650602
   ], 
   [
    "minsky", 
    3, 
    0.060240963855421686
   ], 
   [
    "diamonds", 
    3, 
    0.060240963855421686
   ], 
   [
    "agency", 
    3, 
    0.04819277108433735
   ], 
   [
    "criminal", 
    3, 
    0.03614457831325301
   ], 
   [
    "venezuela", 
    1, 
    0.03614457831325301
   ], 
   [
    "new", 
    3, 
    0.03614457831325301
   ], 
   [
    "parts", 
    3, 
    0.03614457831325301
   ], 
   [
    "success", 
    3, 
    0.03614457831325301
   ], 
   [
    "leonid", 
    2, 
    0.03614457831325301
   ], 
   [
    "power", 
    3, 
    0.03614457831325301
   ], 
   [
    "soviet", 
    1, 
    0.03614457831325301
   ], 
   [
    "general", 
    3, 
    0.03614457831325301
   ], 
   [
    "post", 
    3, 
    0.03614457831325301
   ], 
   [
    "organization", 
    3, 
    0.03614457831325301
   ], 
   [
    "transfer", 
    3, 
    0.024096385542168676
   ], 
   [
    "forces", 
    3, 
    0.024096385542168676
   ], 
   [
    "guns", 
    3, 
    0.024096385542168676
   ], 
   [
    "shipment", 
    3, 
    0.024096385542168676
   ], 
   [
    "shipped", 
    3, 
    0.024096385542168676
   ]
  ], 
  "TopicNum: ": 4
 }
]