[
 {
  "keywords": [
   [
    "minsky", 
    3, 
    0.75
   ], 
   [
    "russia", 
    1, 
    0.16666666666666666
   ], 
   [
    "room", 
    3, 
    0.1
   ], 
   [
    "minsky", 
    3, 
    0.1
   ], 
   [
    "italian", 
    3, 
    0.1
   ], 
   [
    "phone", 
    3, 
    0.1
   ], 
   [
    "belong", 
    3, 
    0.1
   ], 
   [
    "domodedovo", 
    3, 
    0.1
   ], 
   [
    "virote", 
    3, 
    0.1
   ], 
   [
    "english", 
    3, 
    0.1
   ], 
   [
    "june", 
    3, 
    0.1
   ], 
   [
    "military", 
    3, 
    0.1
   ], 
   [
    "exhibition", 
    3, 
    0.1
   ], 
   [
    "yemen", 
    3, 
    0.1
   ], 
   [
    "cid", 
    3, 
    0.1
   ], 
   [
    "landing", 
    3, 
    0.1
   ], 
   [
    "air", 
    3, 
    0.1
   ], 
   [
    "sleeping", 
    3, 
    0.1
   ], 
   [
    "knives", 
    3, 
    0.1
   ], 
   [
    "leonid", 
    2, 
    0.08333333333333333
   ]
  ], 
  "TopicNum: ": 0
 }, 
 {
  "keywords": [
   [
    "ahmed", 
    2, 
    0.10714285714285714
   ], 
   [
    "burj", 
    1, 
    0.09523809523809523
   ], 
   [
    "baltasar", 
    2, 
    0.09523809523809523
   ], 
   [
    "saudi", 
    1, 
    0.07142857142857142
   ], 
   [
    "syria", 
    1, 
    0.07142857142857142
   ], 
   [
    "arabia", 
    1, 
    0.07142857142857142
   ], 
   [
    "arms", 
    3, 
    0.05952380952380952
   ], 
   [
    "nigeria", 
    1, 
    0.047619047619047616
   ], 
   [
    "sold", 
    3, 
    0.047619047619047616
   ], 
   [
    "guns", 
    3, 
    0.03571428571428571
   ], 
   [
    "weeks", 
    3, 
    0.03571428571428571
   ], 
   [
    "yemen", 
    1, 
    0.03571428571428571
   ], 
   [
    "reunion", 
    3, 
    0.023809523809523808
   ], 
   [
    "april", 
    0, 
    0.023809523809523808
   ], 
   [
    "dubai", 
    1, 
    0.023809523809523808
   ], 
   [
    "turkey", 
    1, 
    0.023809523809523808
   ], 
   [
    "professor", 
    2, 
    0.023809523809523808
   ], 
   [
    "arab", 
    2, 
    0.023809523809523808
   ], 
   [
    "weapons", 
    3, 
    0.023809523809523808
   ], 
   [
    "oil", 
    3, 
    0.023809523809523808
   ]
  ], 
  "TopicNum: ": 1
 }, 
 {
  "keywords": [
   [
    "may", 
    0, 
    0.1935483870967742
   ], 
   [
    "jhon", 
    3, 
    0.1
   ], 
   [
    "kasem", 
    3, 
    0.1
   ], 
   [
    "carabobo", 
    3, 
    0.1
   ], 
   [
    "nicolai", 
    3, 
    0.1
   ], 
   [
    "tanya", 
    3, 
    0.1
   ], 
   [
    "plane", 
    3, 
    0.1
   ], 
   [
    "venezuela", 
    1, 
    0.0967741935483871
   ], 
   [
    "lebanon", 
    1, 
    0.0967741935483871
   ], 
   [
    "khouri", 
    2, 
    0.06451612903225806
   ], 
   [
    "gaza", 
    1, 
    0.06451612903225806
   ], 
   [
    "kasem", 
    2, 
    0.06451612903225806
   ], 
   [
    "hombre", 
    2, 
    0.06451612903225806
   ], 
   [
    "birthday", 
    3, 
    0.06451612903225806
   ], 
   [
    "present", 
    0, 
    0.06451612903225806
   ], 
   [
    "jhon", 
    2, 
    0.06451612903225806
   ], 
   [
    "exchange", 
    3, 
    0.06451612903225806
   ], 
   [
    "reunion", 
    3, 
    0.03225806451612903
   ], 
   [
    "april", 
    0, 
    0.03225806451612903
   ], 
   [
    "dubai", 
    1, 
    0.03225806451612903
   ]
  ], 
  "TopicNum: ": 2
 }, 
 {
  "keywords": [
   [
    "nicolai", 
    2, 
    0.2608695652173913
   ], 
   [
    "kenya", 
    1, 
    0.21739130434782608
   ], 
   [
    "iran", 
    1, 
    0.13043478260869565
   ], 
   [
    "pakistan", 
    1, 
    0.13043478260869565
   ], 
   [
    "basra", 
    3, 
    0.1
   ], 
   [
    "bukhari", 
    3, 
    0.1
   ], 
   [
    "tabriz", 
    3, 
    0.1
   ], 
   [
    "address", 
    3, 
    0.1
   ], 
   [
    "ali", 
    3, 
    0.1
   ], 
   [
    "blanks", 
    3, 
    0.1
   ], 
   [
    "lahore", 
    3, 
    0.1
   ], 
   [
    "jhangvi", 
    3, 
    0.1
   ], 
   [
    "left", 
    3, 
    0.1
   ], 
   [
    "narok", 
    3, 
    0.1
   ], 
   [
    "otieno", 
    3, 
    0.1
   ], 
   [
    "unlisted", 
    3, 
    0.1
   ], 
   [
    "kiev", 
    3, 
    0.1
   ], 
   [
    "otieno", 
    2, 
    0.08695652173913043
   ], 
   [
    "nahid", 
    2, 
    0.08695652173913043
   ], 
   [
    "owiti", 
    2, 
    0.08695652173913043
   ]
  ], 
  "TopicNum: ": 3
 }, 
 {
  "keywords": [
   [
    "nigeria", 
    1, 
    0.13114754098360656
   ], 
   [
    "sickness", 
    3, 
    0.08196721311475409
   ], 
   [
    "transfer", 
    3, 
    0.06557377049180328
   ], 
   [
    "funds", 
    3, 
    0.06557377049180328
   ], 
   [
    "columbia", 
    2, 
    0.04918032786885246
   ], 
   [
    "business", 
    3, 
    0.03278688524590164
   ], 
   [
    "meeting", 
    3, 
    0.03278688524590164
   ], 
   [
    "make", 
    3, 
    0.03278688524590164
   ], 
   [
    "finally", 
    3, 
    0.03278688524590164
   ], 
   [
    "take", 
    3, 
    0.03278688524590164
   ], 
   [
    "still", 
    3, 
    0.03278688524590164
   ], 
   [
    "payment", 
    3, 
    0.03278688524590164
   ], 
   [
    "contract", 
    3, 
    0.03278688524590164
   ], 
   [
    "mutual", 
    3, 
    0.03278688524590164
   ], 
   [
    "success", 
    3, 
    0.03278688524590164
   ], 
   [
    "procession", 
    3, 
    0.03278688524590164
   ], 
   [
    "actually", 
    3, 
    0.03278688524590164
   ], 
   [
    "semblance", 
    3, 
    0.03278688524590164
   ], 
   [
    "fetus", 
    3, 
    0.03278688524590164
   ], 
   [
    "goals", 
    3, 
    0.03278688524590164
   ]
  ], 
  "TopicNum: ": 4
 }
]