[
 {
  "keywords": [
   [
    "minsky", 
    3, 
    0.1951219512195122
   ], 
   [
    "barcelona", 
    1, 
    0.17886178861788618
   ], 
   [
    "minsky", 
    3, 
    0.1
   ], 
   [
    "leonid", 
    3, 
    0.1
   ], 
   [
    "room", 
    3, 
    0.1
   ], 
   [
    "diamonds", 
    3, 
    0.1
   ], 
   [
    "italian", 
    3, 
    0.1
   ], 
   [
    "military", 
    3, 
    0.1
   ], 
   [
    "venezuela", 
    3, 
    0.1
   ], 
   [
    "russia", 
    1, 
    0.0975609756097561
   ], 
   [
    "bridge", 
    3, 
    0.0975609756097561
   ], 
   [
    "jorge", 
    2, 
    0.08130081300813008
   ], 
   [
    "beto", 
    3, 
    0.04878048780487805
   ], 
   [
    "leonid", 
    2, 
    0.04878048780487805
   ], 
   [
    "jewels", 
    3, 
    0.04878048780487805
   ], 
   [
    "pyongyang", 
    1, 
    0.04878048780487805
   ], 
   [
    "death", 
    3, 
    0.04878048780487805
   ], 
   [
    "construction", 
    3, 
    0.04878048780487805
   ], 
   [
    "venezuela", 
    1, 
    0.032520325203252036
   ], 
   [
    "civil", 
    3, 
    0.024390243902439025
   ]
  ], 
  "TopicNum: ": 0
 }, 
 {
  "keywords": [
   [
    "giunter", 
    3, 
    0.25
   ], 
   [
    "iran", 
    1, 
    0.125
   ], 
   [
    "ukraine", 
    3, 
    0.125
   ], 
   [
    "saudi", 
    1, 
    0.125
   ], 
   [
    "tanya", 
    2, 
    0.125
   ], 
   [
    "ilyushin", 
    3, 
    0.125
   ], 
   [
    "volkswagons", 
    3, 
    0.125
   ], 
   [
    "ukraine", 
    3, 
    0.1
   ], 
   [
    "tanya", 
    3, 
    0.1
   ], 
   [
    "ilyushin", 
    3, 
    0.1
   ], 
   [
    "flight", 
    3, 
    0.1
   ], 
   [
    "crew", 
    3, 
    0.1
   ], 
   [
    "british", 
    3, 
    0.1
   ], 
   [
    "kiev", 
    3, 
    0.1
   ], 
   [
    "drilling", 
    3, 
    0.1
   ], 
   [
    "airport", 
    3, 
    0.1
   ], 
   [
    "saudi", 
    3, 
    0.1
   ], 
   [
    "moscow", 
    3, 
    0.1
   ], 
   [
    "arms", 
    3, 
    0.1
   ], 
   [
    "yemen", 
    3, 
    0.1
   ]
  ], 
  "TopicNum: ": 1
 }, 
 {
  "keywords": [
   [
    "kenya", 
    1, 
    0.42857142857142855
   ], 
   [
    "mombasa", 
    1, 
    0.42857142857142855
   ], 
   [
    "british", 
    1, 
    0.14285714285714285
   ], 
   [
    "operation", 
    3, 
    0.1
   ], 
   [
    "kasem", 
    3, 
    0.1
   ], 
   [
    "watching", 
    3, 
    0.1
   ], 
   [
    "moscow", 
    3, 
    0.1
   ], 
   [
    "project", 
    3, 
    0.1
   ], 
   [
    "exhibition", 
    3, 
    0.1
   ], 
   [
    "hard", 
    3, 
    0.1
   ], 
   [
    "air", 
    3, 
    0.1
   ], 
   [
    "southern", 
    3, 
    0.1
   ], 
   [
    "regional", 
    3, 
    0.1
   ], 
   [
    "russia", 
    3, 
    0.1
   ], 
   [
    "mfj", 
    3, 
    0.1
   ], 
   [
    "cigarette", 
    3, 
    0.1
   ], 
   [
    "sudan", 
    3, 
    0.1
   ], 
   [
    "rosoboronexport", 
    3, 
    0.1
   ], 
   [
    "sldf", 
    3, 
    0.1
   ], 
   [
    "gashi", 
    3, 
    0.1
   ]
  ], 
  "TopicNum: ": 2
 }, 
 {
  "keywords": [
   [
    "nigeria", 
    1, 
    0.3333333333333333
   ], 
   [
    "energy", 
    3, 
    0.16666666666666666
   ], 
   [
    "minerals", 
    3, 
    0.16666666666666666
   ], 
   [
    "funsho", 
    2, 
    0.16666666666666666
   ], 
   [
    "nigeria", 
    3, 
    0.1
   ], 
   [
    "saudi", 
    3, 
    0.1
   ], 
   [
    "contract", 
    3, 
    0.1
   ], 
   [
    "communication", 
    3, 
    0.1
   ], 
   [
    "transaction", 
    3, 
    0.1
   ], 
   [
    "funds", 
    3, 
    0.1
   ], 
   [
    "amount", 
    3, 
    0.1
   ], 
   [
    "guns", 
    3, 
    0.1
   ], 
   [
    "much", 
    3, 
    0.1
   ], 
   [
    "agency", 
    3, 
    0.1
   ], 
   [
    "arabian", 
    3, 
    0.1
   ], 
   [
    "monetary", 
    3, 
    0.1
   ], 
   [
    "ahmed", 
    3, 
    0.1
   ], 
   [
    "bangkok", 
    3, 
    0.1
   ], 
   [
    "civil", 
    3, 
    0.08333333333333333
   ], 
   [
    "joetomsk", 
    2, 
    0.08333333333333333
   ]
  ], 
  "TopicNum: ": 3
 }, 
 {
  "keywords": [
   [
    "borodinski", 
    3, 
    0.1
   ], 
   [
    "mikhail", 
    3, 
    0.1
   ], 
   [
    "dubai", 
    1, 
    0.09917355371900827
   ], 
   [
    "project", 
    3, 
    0.09917355371900827
   ], 
   [
    "george", 
    2, 
    0.08264462809917356
   ], 
   [
    "russia", 
    1, 
    0.08264462809917356
   ], 
   [
    "joetomsk", 
    2, 
    0.0743801652892562
   ], 
   [
    "soltan", 
    2, 
    0.049586776859504134
   ], 
   [
    "borodinski", 
    2, 
    0.049586776859504134
   ], 
   [
    "moscow", 
    1, 
    0.049586776859504134
   ], 
   [
    "water", 
    3, 
    0.049586776859504134
   ], 
   [
    "lagos", 
    1, 
    0.049586776859504134
   ], 
   [
    "health", 
    3, 
    0.049586776859504134
   ], 
   [
    "mikhail", 
    2, 
    0.049586776859504134
   ], 
   [
    "investment", 
    3, 
    0.049586776859504134
   ], 
   [
    "transaction", 
    3, 
    0.03305785123966942
   ], 
   [
    "april", 
    0, 
    0.03305785123966942
   ], 
   [
    "families", 
    3, 
    0.03305785123966942
   ], 
   [
    "dombrovski", 
    2, 
    0.03305785123966942
   ], 
   [
    "email", 
    3, 
    0.03305785123966942
   ]
  ], 
  "TopicNum: ": 4
 }, 
 {
  "keywords": [
   [
    "maulana", 
    2, 
    0.2857142857142857
   ], 
   [
    "akram", 
    2, 
    0.2857142857142857
   ], 
   [
    "pakistan", 
    1, 
    0.2857142857142857
   ], 
   [
    "april", 
    0, 
    0.14285714285714285
   ], 
   [
    "basra", 
    3, 
    0.1
   ], 
   [
    "akram", 
    3, 
    0.1
   ], 
   [
    "belong", 
    3, 
    0.1
   ], 
   [
    "per", 
    3, 
    0.1
   ], 
   [
    "tebilaead", 
    3, 
    0.1
   ], 
   [
    "bukhari", 
    3, 
    0.1
   ], 
   [
    "maulana", 
    3, 
    0.1
   ], 
   [
    "april", 
    3, 
    0.1
   ], 
   [
    "tanya", 
    3, 
    0.1
   ], 
   [
    "left", 
    3, 
    0.1
   ], 
   [
    "men", 
    3, 
    0.1
   ], 
   [
    "communication", 
    3, 
    0.1
   ], 
   [
    "transaction", 
    3, 
    0.1
   ], 
   [
    "haq", 
    3, 
    0.1
   ], 
   [
    "bank", 
    3, 
    0.1
   ], 
   [
    "karachi", 
    3, 
    0.1
   ]
  ], 
  "TopicNum: ": 5
 }, 
 {
  "keywords": [
   [
    "ahmed", 
    2, 
    0.11188811188811189
   ], 
   [
    "vwhombre", 
    2, 
    0.11188811188811189
   ], 
   [
    "jhon", 
    3, 
    0.1
   ], 
   [
    "jtomski", 
    3, 
    0.1
   ], 
   [
    "syria", 
    1, 
    0.08391608391608392
   ], 
   [
    "sviatoslavich", 
    3, 
    0.08391608391608392
   ], 
   [
    "april", 
    0, 
    0.06293706293706294
   ], 
   [
    "venezuela", 
    1, 
    0.04195804195804196
   ], 
   [
    "jhon", 
    2, 
    0.04195804195804196
   ], 
   [
    "green", 
    2, 
    0.04195804195804196
   ], 
   [
    "textbook", 
    3, 
    0.04195804195804196
   ], 
   [
    "professor", 
    2, 
    0.04195804195804196
   ], 
   [
    "igor", 
    2, 
    0.04195804195804196
   ], 
   [
    "nicolai", 
    2, 
    0.04195804195804196
   ], 
   [
    "delivery", 
    3, 
    0.04195804195804196
   ], 
   [
    "farming", 
    3, 
    0.04195804195804196
   ], 
   [
    "arab", 
    2, 
    0.04195804195804196
   ], 
   [
    "hospital", 
    1, 
    0.04195804195804196
   ], 
   [
    "pontiac", 
    3, 
    0.04195804195804196
   ], 
   [
    "savvytraveladvice", 
    3, 
    0.04195804195804196
   ]
  ], 
  "TopicNum: ": 6
 }, 
 {
  "keywords": [
   [
    "yemen", 
    1, 
    0.15384615384615385
   ], 
   [
    "kasem", 
    2, 
    0.11538461538461539
   ], 
   [
    "lebanon", 
    1, 
    0.11538461538461539
   ], 
   [
    "sickness", 
    3, 
    0.11538461538461539
   ], 
   [
    "kasem", 
    3, 
    0.1
   ], 
   [
    "khouri", 
    3, 
    0.1
   ], 
   [
    "yemen", 
    3, 
    0.1
   ], 
   [
    "otieno", 
    3, 
    0.1
   ], 
   [
    "tit", 
    3, 
    0.1
   ], 
   [
    "anka", 
    3, 
    0.1
   ], 
   [
    "ahmed", 
    3, 
    0.1
   ], 
   [
    "aden", 
    3, 
    0.1
   ], 
   [
    "jtomski", 
    2, 
    0.09615384615384616
   ], 
   [
    "khouri", 
    2, 
    0.057692307692307696
   ], 
   [
    "anka", 
    2, 
    0.057692307692307696
   ], 
   [
    "sana", 
    1, 
    0.057692307692307696
   ], 
   [
    "aden", 
    2, 
    0.057692307692307696
   ], 
   [
    "otieno", 
    2, 
    0.057692307692307696
   ], 
   [
    "columbia", 
    2, 
    0.057692307692307696
   ], 
   [
    "raleigh", 
    3, 
    0.057692307692307696
   ]
  ], 
  "TopicNum: ": 7
 }
]